pandas_indicators/__init__.py
pandas_indicators/core.py
pandas_indicators/custom.py
pandas_indicators/candles/__init__.py
pandas_indicators/candles/cdl_doji.py
pandas_indicators/candles/cdl_inside.py
pandas_indicators/candles/cdl_pattern.py
pandas_indicators/candles/cdl_z.py
pandas_indicators/candles/ha.py
pandas_indicators/cycles/__init__.py
pandas_indicators/cycles/ebsw.py
pandas_indicators/momentum/__init__.py
pandas_indicators/momentum/ao.py
pandas_indicators/momentum/apo.py
pandas_indicators/momentum/bias.py
pandas_indicators/momentum/bop.py
pandas_indicators/momentum/brar.py
pandas_indicators/momentum/cci.py
pandas_indicators/momentum/cfo.py
pandas_indicators/momentum/cg.py
pandas_indicators/momentum/cmo.py
pandas_indicators/momentum/coppock.py
pandas_indicators/momentum/cti.py
pandas_indicators/momentum/dm.py
pandas_indicators/momentum/er.py
pandas_indicators/momentum/eri.py
pandas_indicators/momentum/fisher.py
pandas_indicators/momentum/inertia.py
pandas_indicators/momentum/kdj.py
pandas_indicators/momentum/kst.py
pandas_indicators/momentum/macd.py
pandas_indicators/momentum/mom.py
pandas_indicators/momentum/pgo.py
pandas_indicators/momentum/ppo.py
pandas_indicators/momentum/psl.py
pandas_indicators/momentum/pvo.py
pandas_indicators/momentum/qqe.py
pandas_indicators/momentum/roc.py
pandas_indicators/momentum/rsi.py
pandas_indicators/momentum/rsx.py
pandas_indicators/momentum/rvgi.py
pandas_indicators/momentum/slope.py
pandas_indicators/momentum/smi.py
pandas_indicators/momentum/squeeze.py
pandas_indicators/momentum/squeeze_pro.py
pandas_indicators/momentum/stc.py
pandas_indicators/momentum/stoch.py
pandas_indicators/momentum/stochrsi.py
pandas_indicators/momentum/td_seq.py
pandas_indicators/momentum/trix.py
pandas_indicators/momentum/tsi.py
pandas_indicators/momentum/uo.py
pandas_indicators/momentum/willr.py
pandas_indicators/overlap/__init__.py
pandas_indicators/overlap/alma.py
pandas_indicators/overlap/dema.py
pandas_indicators/overlap/ema.py
pandas_indicators-1.0.0.dist-info/METADATA
pandas_indicators-1.0.0.dist-info/WHEEL
pandas_indicators-1.0.0.dist-info/licenses/LICENSE
pandas_indicators-1.0.0.dist-info/RECORD
