Metadata-Version: 2.3
Name: pandas-indicators
Version: 1.0.0
Summary: preform indicators analysis on a pandas dataframes
Project-URL: Homepage, https://github.com/osama-dev-repo/indicators-engine.git
Project-URL: Issues, https://github.com/osama-dev-repo/indicators-engine.git/issues
Author: OSAMA
Classifier: License :: OSI Approved :: MIT License
Classifier: Operating System :: OS Independent
Classifier: Programming Language :: Python :: 3
Requires-Python: >=3.12
